py_contract_codegen/__init__.py
py_contract_codegen/cli.py
py_contract_codegen/generated/contract/crypto_kitties.py
py_contract_codegen/generated/contract/uniswap_v3.py
py_contract_codegen/generated/contract/usdt.py
py_contract_codegen/modules/abi.py
py_contract_codegen/modules/code_generator.py
py_contract_codegen/modules/enums.py
py_contract_codegen/modules/etherscan.py
py_contract_codegen/modules/exceptions.py
py_contract_codegen/template/contract.web3_v6.jinja2
py_contract_codegen/template/contract.web3_v7.jinja2
py_contract_codegen/tests/test_cli.py
py_contract_codegen/tests/modules/test_abi.py
py_contract_codegen/tests/modules/test_code_generator.py
py_contract_codegen/tests/modules/test_etherscan.py
py_contract_codegen-0.1.3.dist-info/METADATA
py_contract_codegen-0.1.3.dist-info/WHEEL
py_contract_codegen-0.1.3.dist-info/entry_points.txt
py_contract_codegen-0.1.3.dist-info/licenses/LICENSE
py_contract_codegen-0.1.3.dist-info/RECORD
