Metadata-Version: 2.4
Name: py-contract-codegen
Version: 0.1.3
Summary: A cli tool to generate Python code from EVM ABI.
Author: Naoki Maeda
License-File: LICENSE
Requires-Python: >=3.11
Requires-Dist: httpx>=0.27.0
Requires-Dist: jinja2>=3.1.4
Requires-Dist: typer>=0.12.3
Requires-Dist: web3==7.11.0
